{
  "id": "a9ab8c66de974b9ebc55431d3d20d1aa",
  "codec": "webp",
  "task": "encode_complexity",
  "dataset": "clip_naflex",
  "input_resolution": [
    null,
    null
  ],
  "n_images": 256,
  "operating_point": {
    "type": "quality",
    "value": 25,
    "extras": {}
  },
  "stages": [
    "encode"
  ],
  "config": {
    "backend": "pillow",
    "format": "WEBP",
    "quality": 25
  },
  "testbed": {
    "hostname": "ecen-a94017",
    "os": "Linux 6.8.0-111-generic",
    "python": "3.12.3",
    "torch": "2.11.0+cu130",
    "pil_version": "12.2.0",
    "device": "cpu",
    "n_warmup": 1,
    "n_measurement": 5,
    "cpu_model": "AMD EPYC 9354 32-Core Processor",
    "gpu_model": null
  },
  "results": {
    "throughput": {
      "median_MPx_per_s": 14.715021909215423,
      "mean_MPx_per_s": 14.858468885102535,
      "total_per_image": {
        "median": 0.004401657497510314,
        "mean": 0.004405912400579836
      },
      "aggregation": "geometric_mean_over_per_image_MPx_per_s"
    },
    "stages": {
      "encode": {
        "median": 0.004401657497510314,
        "mean": 0.004405912400579836
      }
    }
  },
  "harness": {
    "module": "seaotter.eval.encode_complexity",
    "n_warmup": 1,
    "n_measurement": 5,
    "n_total_inferences": 1280,
    "wallclock_runtime_s": 5.645217339042574
  },
  "shape_distribution": {
    "224x288": 143,
    "192x320": 24,
    "256x256": 30,
    "288x224": 52,
    "160x352": 1,
    "320x192": 6
  }
}